dash_summernote/DashSummernote.py
dash_summernote/__init__.py
dash_summernote/_imports_.py
dash_summernote/dash_summernote.min.js
dash_summernote/dash_summernote.min.js.map
dash_summernote/metadata.json
dash_summernote/package-info.json
dash_summernote-0.0.1.dist-info/LICENSE
dash_summernote-0.0.1.dist-info/METADATA
dash_summernote-0.0.1.dist-info/WHEEL
dash_summernote-0.0.1.dist-info/top_level.txt
dash_summernote-0.0.1.dist-info/RECORD
